Metadata-Version: 1.0
Name: translapi
Version: 1.0.6
Summary: Google Translate API
Home-page: UNKNOWN
Author: Adam Jenca
Author-email: jenca.a@gjh.sk
License: UNKNOWN
Platform: UNKNOWN
